[{"line":2,"elements":[{"line":4,"name":"ortak adim","description":"","type":"background","keyword":"Background","steps":[{"result":{"duration":24751870400,"status":"passed"},"line":5,"name":"kullanici amazon anasayfasinda","match":{"location":"stepDefinitions.AmazonStepDefinitions.kullanici_amazon_anasayfasinda()"},"keyword":"Given "}]},{"start_timestamp":"2022-06-09T18:08:20.061Z","line":12,"name":"TC05 kullanici amazonda Java aratir","description":"","id":"us1002-kullanici-ortak-adimlari-background-ile-calistirir;tc05-kullanici-amazonda-java-aratir","after":[{"result":{"duration":3572205900,"status":"passed"},"match":{"location":"stepDefinitions.Hooks.tearDown(io.cucumber.java.Scenario)"}}],"type":"scenario","keyword":"Scenario","steps":[{"result":{"duration":19974544000,"status":"passed"},"line":13,"name":"kullanici Java icin arama yapar","match":{"location":"stepDefinitions.AmazonStepDefinitions.kullanici_java_icin_arama_yapar()"},"keyword":"And "},{"result":{"duration":113518500,"status":"passed"},"line":14,"name":"sonuclarin Java icerdigini test eder","match":{"location":"stepDefinitions.AmazonStepDefinitions.sonuclarin_java_icerdigini_test_eder()"},"keyword":"Then "},{"result":{"duration":204016100,"status":"passed"},"line":15,"name":"sayfayi kapatir","match":{"location":"stepDefinitions.AmazonStepDefinitions.sayfayi_kapatir()"},"keyword":"And "}],"tags":[{"name":"@wip"},{"name":"@pr2"}]}],"name":"US1002 Kullanici ortak adimlari Background ile calistirir","description":"","id":"us1002-kullanici-ortak-adimlari-background-ile-calistirir","keyword":"Feature","uri":"file:src/test/resources/features/US1002_backgroundKullanim.feature","tags":[{"name":"@wip","type":"Tag","location":{"line":1,"column":1}}]},{"line":1,"elements":[{"start_timestamp":"2022-06-09T18:09:08.963Z","line":4,"name":"TC15 herokuapp'dan delete butonu calismali","description":"","id":"us1010-herokuapp-delete-testi;tc15-herokuapp-dan-delete-butonu-calismali","after":[{"result":{"duration":7136366800,"status":"passed"},"match":{"location":"stepDefinitions.Hooks.tearDown(io.cucumber.java.Scenario)"}}],"type":"scenario","keyword":"Scenario","steps":[{"result":{"duration":8369335100,"status":"passed"},"line":5,"name":"kullanici \"herokuappUrl\" anasayfasinda","match":{"arguments":[{"val":"\"herokuappUrl\"","offset":10}],"location":"stepDefinitions.AmazonStepDefinitions.kullanici_anasayfasinda(java.lang.String)"},"keyword":"Given "},{"result":{"duration":117009800,"status":"passed"},"line":6,"name":"add element butonuna basar","match":{"location":"stepDefinitions.HerokuStepDefinitions.add_element_butonuna_basar()"},"keyword":"And "},{"result":{"duration":3010686400,"status":"passed"},"line":7,"name":"kullanici 3 sn bekler","match":{"arguments":[{"val":"3","offset":10}],"location":"stepDefinitions.AmazonStepDefinitions.kullaniciSnBekler(int)"},"keyword":"And "},{"result":{"duration":90008500,"status":"passed"},"line":8,"name":"Delete butonu gorunur oluncaya kadar bekler","match":{"location":"stepDefinitions.HerokuStepDefinitions.delete_butonu_gorunur_oluncaya_kadar_bekler()"},"keyword":"Then "},{"result":{"duration":45005400,"status":"passed"},"line":9,"name":"Delete butonunun gorunur oldugunu test eder","match":{"location":"stepDefinitions.HerokuStepDefinitions.delete_butonunun_gorunur_oldugunu_test_eder()"},"keyword":"And "},{"result":{"duration":66004200,"status":"passed"},"line":10,"name":"Delete butonuna basar","match":{"location":"stepDefinitions.HerokuStepDefinitions.delete_butonuna_basar()"},"keyword":"Then "},{"result":{"duration":15076347800,"status":"passed"},"line":11,"name":"Delete butonunun gorunmedigini test eder","match":{"location":"stepDefinitions.HerokuStepDefinitions.delete_butonunun_gorunmedigini_test_eder()"},"keyword":"And "},{"result":{"duration":143009000,"status":"passed"},"line":12,"name":"sayfayi kapatir","match":{"location":"stepDefinitions.AmazonStepDefinitions.sayfayi_kapatir()"},"keyword":"And "}],"tags":[{"name":"@heroku"},{"name":"@sirali"},{"name":"@pr2"}]}],"name":"US1010 herokuapp Delete testi","description":"","id":"us1010-herokuapp-delete-testi","keyword":"Feature","uri":"file:src/test/resources/features/US1010_Herokuapp.feature","tags":[]}]